scratchdata/__init__.py
scratchdata/main.py
scratchdata/stats.py
scratchdata-0.1.2.dist-info/METADATA
scratchdata-0.1.2.dist-info/WHEEL
scratchdata-0.1.2.dist-info/top_level.txt
scratchdata-0.1.2.dist-info/RECORD
