Metadata-Version: 2.1
Name: scratchdata
Version: 0.1.2
Summary: Module for data from scratch
Home-page: UNKNOWN
Author: Vyacheslav C.
Author-email: <vyacheslav_h@icloud.com>
License: UNKNOWN
Keywords: python,scratch,data,scraper
Platform: UNKNOWN
Classifier: Development Status :: 1 - Planning
Classifier: Intended Audience :: Developers
Classifier: Programming Language :: Python :: 3
Classifier: Operating System :: Unix
Classifier: Operating System :: MacOS :: MacOS X
Classifier: Operating System :: Microsoft :: Windows
Requires-Dist: requests
